sakthiselvan/__init__.py
sakthiselvan/example.py
sakthiselvan-0.1.0.dist-info/LICENCE
sakthiselvan-0.1.0.dist-info/METADATA
sakthiselvan-0.1.0.dist-info/WHEEL
sakthiselvan-0.1.0.dist-info/top_level.txt
sakthiselvan-0.1.0.dist-info/RECORD
