Metadata-Version: 2.1
Name: sakthiselvan
Version: 0.1.0
Summary: A utility module for string manipulation, character encoding, sorting, and list operations.
Author-email: SakthiSelvan <ssakthitselvan7@gmail.com>
License: MIT
Project-URL: Homepage, https://github.com/yourusername/mymodule
Project-URL: Documentation, https://github.com/yourusername/mymodule/docs
Project-URL: Issue Tracker, https://github.com/yourusername/mymodule/issues
Keywords: string-manipulation,sorting,character-encoding,utilities
Classifier: Programming Language :: Python :: 3
Classifier: License :: OSI Approved :: MIT License
Classifier: Operating System :: OS Independent
Requires-Python: >=3.6
License-File: LICENCE
